corona_analytics/__init__.py
coronapy/__init__.py
corona_analytics-0.1.dist-info/LICENSE
corona_analytics-0.1.dist-info/METADATA
corona_analytics-0.1.dist-info/WHEEL
corona_analytics-0.1.dist-info/top_level.txt
corona_analytics-0.1.dist-info/RECORD
