Metadata-Version: 2.1
Name: corona-analytics
Version: 0.1
Summary: Simple python module for accessing Coronavirus datasources.
Home-page: https://github.com/gisfromscratch/corona-py
Author: Jan Tschada
Author-email: gisfromscratch@live.de
License: UNKNOWN
Platform: UNKNOWN
Classifier: Programming Language :: Python :: 3
Classifier: License :: OSI Approved :: Apache Software License
Classifier: Operating System :: OS Independent
Requires-Dist: pandas (>=1.0.0)
